[
  {
    "id": "itad-018d937f-73c0-72fc-a",
    "title": "Oddsparks: An Automation Adventure",
    "slug": "oddsparks-an-automation-adventure",
    "type": "game",
    "thumb": "https://assets.isthereanydeal.com/018d937f-73c0-72fc-a883-956f6381dce4/banner400.jpg?t=1776864934",
    "store": {
      "name": "Epic Game Store",
      "url": "https://itad.link/018d959b-1092-71e1-a6b7-ceda3fb5a461/"
    },
    "price": {
      "current": 0,
      "regular": 32000,
      "currency": "KRW",
      "cut": 100
    },
    "history": {
      "lowest": 16000,
      "lowest_date": null,
      "is_lowest": true,
      "is_store_low": false
    },
    "meta": {
      "steam_appid": 2540410,
      "rating": null,
      "reviews": null,
      "players_current": null,
      "owners_estimated": null,
      "tags": [],
      "platforms": [],
      "drm": "Epic"
    },
    "popularity_score": 0.65,
    "source": "itad",
    "itad_slug": "oddsparks-an-automation-adventure",
    "flag": "N",
    "updated_at": "2026-05-01T11:39:21.461847+00:00",
    "steam_meta": {
      "review_score": "Mixed",
      "review_pct": 60,
      "review_count": 43,
      "languages": [
        "영어"
      ],
      "has_korean": 0
    },
    "price_history": [
      {
        "date": "2026-04-30",
        "price": 0.0,
        "discount": 100
      },
      {
        "date": "2026-04-30",
        "price": 0.0,
        "discount": 100
      },
      {
        "date": "2026-04-30",
        "price": 0.0,
        "discount": 100
      },
      {
        "date": "2026-04-30",
        "price": 0.0,
        "discount": 100
      },
      {
        "date": "2026-04-30",
        "price": 0.0,
        "discount": 100
      },
      {
        "date": "2026-04-30",
        "price": 0.0,
        "discount": 100
      },
      {
        "date": "2026-04-30",
        "price": 0.0,
        "discount": 100
      },
      {
        "date": "2026-05-01",
        "price": 0.0,
        "discount": 100
      },
      {
        "date": "2026-05-01",
        "price": 0.0,
        "discount": 100
      },
      {
        "date": "2026-05-01",
        "price": 0.0,
        "discount": 100
      },
      {
        "date": "2026-05-01",
        "price": 0.0,
        "discount": 100
      },
      {
        "date": "2026-05-01",
        "price": 0.0,
        "discount": 100
      },
      {
        "date": "2026-05-01",
        "price": 0.0,
        "discount": 100
      },
      {
        "date": "2026-05-01",
        "price": 0.0,
        "discount": 100
      },
      {
        "date": "2026-05-01",
        "price": 0.0,
        "discount": 100
      },
      {
        "date": "2026-05-01",
        "price": 0.0,
        "discount": 100
      },
      {
        "date": "2026-05-01",
        "price": 0.0,
        "discount": 100
      },
      {
        "date": "2026-05-01",
        "price": 0.0,
        "discount": 100
      },
      {
        "date": "2026-05-01",
        "price": 0.0,
        "discount": 100
      }
    ]
  },
  {
    "id": "itad-018d937f-6144-7057-a",
    "title": "Hogwarts Legacy",
    "slug": "hogwarts-legacy",
    "type": "game",
    "thumb": "https://assets.isthereanydeal.com/018d937f-6144-7057-ad1c-0e99a3a71797/banner400.jpg?t=1773933608",
    "store": {
      "name": "Epic Game Store",
      "url": "https://itad.link/018d959c-f86e-7393-896d-a27747ac7e91/"
    },
    "price": {
      "current": 0,
      "regular": 79800,
      "currency": "KRW",
      "cut": 100
    },
    "history": {
      "lowest": 7100,
      "lowest_date": null,
      "is_lowest": true,
      "is_store_low": false
    },
    "meta": {
      "steam_appid": null,
      "rating": null,
      "reviews": null,
      "players_current": null,
      "owners_estimated": null,
      "tags": [],
      "platforms": [],
      "drm": "Epic"
    },
    "popularity_score": 0.65,
    "source": "itad",
    "itad_slug": "hogwarts-legacy",
    "flag": "N",
    "updated_at": "2026-05-01T11:39:21.461999+00:00",
    "price_history": [
      {
        "date": "2026-04-30",
        "price": 0.0,
        "discount": 100
      },
      {
        "date": "2026-04-30",
        "price": 0.0,
        "discount": 100
      },
      {
        "date": "2026-04-30",
        "price": 0.0,
        "discount": 100
      },
      {
        "date": "2026-04-30",
        "price": 0.0,
        "discount": 100
      },
      {
        "date": "2026-04-30",
        "price": 0.0,
        "discount": 100
      },
      {
        "date": "2026-04-30",
        "price": 0.0,
        "discount": 100
      },
      {
        "date": "2026-04-30",
        "price": 0.0,
        "discount": 100
      },
      {
        "date": "2026-05-01",
        "price": 0.0,
        "discount": 100
      },
      {
        "date": "2026-05-01",
        "price": 0.0,
        "discount": 100
      },
      {
        "date": "2026-05-01",
        "price": 0.0,
        "discount": 100
      },
      {
        "date": "2026-05-01",
        "price": 0.0,
        "discount": 100
      },
      {
        "date": "2026-05-01",
        "price": 0.0,
        "discount": 100
      },
      {
        "date": "2026-05-01",
        "price": 0.0,
        "discount": 100
      },
      {
        "date": "2026-05-01",
        "price": 0.0,
        "discount": 100
      },
      {
        "date": "2026-05-01",
        "price": 0.0,
        "discount": 100
      },
      {
        "date": "2026-05-01",
        "price": 0.0,
        "discount": 100
      },
      {
        "date": "2026-05-01",
        "price": 0.0,
        "discount": 100
      },
      {
        "date": "2026-05-01",
        "price": 0.0,
        "discount": 100
      },
      {
        "date": "2026-05-01",
        "price": 0.0,
        "discount": 100
      }
    ]
  },
  {
    "id": "itad-0197b193-f6e7-7162-8",
    "title": "Ultimate Chess Suite : 1M Puzzles & AI",
    "slug": "ultimate-chess-suite-1m-puzzles-ai",
    "type": null,
    "thumb": "",
    "store": {
      "name": "Microsoft Store",
      "url": "https://itad.link/0197b193-f6de-73e2-8879-306c6cd487c2/"
    },
    "price": {
      "current": 0,
      "regular": 13900,
      "currency": "KRW",
      "cut": 100
    },
    "history": {
      "lowest": 1200,
      "lowest_date": null,
      "is_lowest": true,
      "is_store_low": false
    },
    "meta": {
      "steam_appid": null,
      "rating": null,
      "reviews": null,
      "players_current": null,
      "owners_estimated": null,
      "tags": [],
      "platforms": [
        "windows"
      ],
      "drm": "Microsoft Store"
    },
    "popularity_score": 0.65,
    "source": "itad",
    "itad_slug": "ultimate-chess-suite-1m-puzzles-and-ai",
    "flag": "H",
    "updated_at": "2026-05-01T11:39:21.462014+00:00",
    "price_history": [
      {
        "date": "2026-04-23",
        "price": 0.0,
        "discount": 100
      },
      {
        "date": "2026-04-23",
        "price": 0.0,
        "discount": 100
      },
      {
        "date": "2026-04-23",
        "price": 0.0,
        "discount": 100
      },
      {
        "date": "2026-04-23",
        "price": 0.0,
        "discount": 100
      },
      {
        "date": "2026-04-23",
        "price": 0.0,
        "discount": 100
      },
      {
        "date": "2026-04-23",
        "price": 0.0,
        "discount": 100
      },
      {
        "date": "2026-04-23",
        "price": 0.0,
        "discount": 100
      },
      {
        "date": "2026-04-23",
        "price": 0.0,
        "discount": 100
      },
      {
        "date": "2026-04-23",
        "price": 0.0,
        "discount": 100
      },
      {
        "date": "2026-04-23",
        "price": 0.0,
        "discount": 100
      },
      {
        "date": "2026-04-23",
        "price": 0.0,
        "discount": 100
      },
      {
        "date": "2026-04-24",
        "price": 0.0,
        "discount": 100
      },
      {
        "date": "2026-04-24",
        "price": 0.0,
        "discount": 100
      },
      {
        "date": "2026-04-24",
        "price": 0.0,
        "discount": 100
      },
      {
        "date": "2026-04-24",
        "price": 0.0,
        "discount": 100
      },
      {
        "date": "2026-04-24",
        "price": 0.0,
        "discount": 100
      },
      {
        "date": "2026-04-24",
        "price": 0.0,
        "discount": 100
      },
      {
        "date": "2026-04-24",
        "price": 0.0,
        "discount": 100
      },
      {
        "date": "2026-04-24",
        "price": 0.0,
        "discount": 100
      },
      {
        "date": "2026-04-24",
        "price": 0.0,
        "discount": 100
      },
      {
        "date": "2026-04-24",
        "price": 0.0,
        "discount": 100
      },
      {
        "date": "2026-04-25",
        "price": 0.0,
        "discount": 100
      },
      {
        "date": "2026-04-25",
        "price": 0.0,
        "discount": 100
      },
      {
        "date": "2026-04-25",
        "price": 0.0,
        "discount": 100
      },
      {
        "date": "2026-04-25",
        "price": 0.0,
        "discount": 100
      },
      {
        "date": "2026-04-25",
        "price": 0.0,
        "discount": 100
      },
      {
        "date": "2026-04-25",
        "price": 0.0,
        "discount": 100
      },
      {
        "date": "2026-04-25",
        "price": 0.0,
        "discount": 100
      },
      {
        "date": "2026-04-25",
        "price": 0.0,
        "discount": 100
      },
      {
        "date": "2026-04-25",
        "price": 0.0,
        "discount": 100
      },
      {
        "date": "2026-04-25",
        "price": 0.0,
        "discount": 100
      },
      {
        "date": "2026-04-25",
        "price": 0.0,
        "discount": 100
      },
      {
        "date": "2026-04-25",
        "price": 0.0,
        "discount": 100
      },
      {
        "date": "2026-04-25",
        "price": 0.0,
        "discount": 100
      },
      {
        "date": "2026-04-25",
        "price": 0.0,
        "discount": 100
      },
      {
        "date": "2026-04-25",
        "price": 0.0,
        "discount": 100
      },
      {
        "date": "2026-04-25",
        "price": 0.0,
        "discount": 100
      },
      {
        "date": "2026-04-25",
        "price": 0.0,
        "discount": 100
      },
      {
        "date": "2026-04-25",
        "price": 0.0,
        "discount": 100
      },
      {
        "date": "2026-04-25",
        "price": 0.0,
        "discount": 100
      },
      {
        "date": "2026-04-25",
        "price": 0.0,
        "discount": 100
      },
      {
        "date": "2026-04-25",
        "price": 0.0,
        "discount": 100
      },
      {
        "date": "2026-04-25",
        "price": 0.0,
        "discount": 100
      },
      {
        "date": "2026-04-25",
        "price": 0.0,
        "discount": 100
      },
      {
        "date": "2026-04-26",
        "price": 0.0,
        "discount": 100
      },
      {
        "date": "2026-04-26",
        "price": 0.0,
        "discount": 100
      },
      {
        "date": "2026-04-26",
        "price": 0.0,
        "discount": 100
      },
      {
        "date": "2026-04-26",
        "price": 0.0,
        "discount": 100
      },
      {
        "date": "2026-04-26",
        "price": 0.0,
        "discount": 100
      },
      {
        "date": "2026-04-26",
        "price": 0.0,
        "discount": 100
      },
      {
        "date": "2026-04-26",
        "price": 0.0,
        "discount": 100
      },
      {
        "date": "2026-04-26",
        "price": 0.0,
        "discount": 100
      },
      {
        "date": "2026-04-26",
        "price": 0.0,
        "discount": 100
      },
      {
        "date": "2026-04-26",
        "price": 0.0,
        "discount": 100
      },
      {
        "date": "2026-04-26",
        "price": 0.0,
        "discount": 100
      },
      {
        "date": "2026-04-26",
        "price": 0.0,
        "discount": 100
      },
      {
        "date": "2026-04-26",
        "price": 0.0,
        "discount": 100
      },
      {
        "date": "2026-04-26",
        "price": 0.0,
        "discount": 100
      },
      {
        "date": "2026-04-26",
        "price": 0.0,
        "discount": 100
      },
      {
        "date": "2026-04-26",
        "price": 0.0,
        "discount": 100
      },
      {
        "date": "2026-04-26",
        "price": 0.0,
        "discount": 100
      },
      {
        "date": "2026-04-26",
        "price": 0.0,
        "discount": 100
      },
      {
        "date": "2026-04-26",
        "price": 0.0,
        "discount": 100
      },
      {
        "date": "2026-04-26",
        "price": 0.0,
        "discount": 100
      },
      {
        "date": "2026-04-27",
        "price": 0.0,
        "discount": 100
      },
      {
        "date": "2026-04-27",
        "price": 0.0,
        "discount": 100
      },
      {
        "date": "2026-04-27",
        "price": 0.0,
        "discount": 100
      },
      {
        "date": "2026-04-27",
        "price": 0.0,
        "discount": 100
      },
      {
        "date": "2026-04-27",
        "price": 0.0,
        "discount": 100
      },
      {
        "date": "2026-04-27",
        "price": 0.0,
        "discount": 100
      },
      {
        "date": "2026-04-27",
        "price": 0.0,
        "discount": 100
      },
      {
        "date": "2026-04-27",
        "price": 0.0,
        "discount": 100
      },
      {
        "date": "2026-04-27",
        "price": 0.0,
        "discount": 100
      },
      {
        "date": "2026-04-27",
        "price": 0.0,
        "discount": 100
      },
      {
        "date": "2026-04-27",
        "price": 0.0,
        "discount": 100
      },
      {
        "date": "2026-04-27",
        "price": 0.0,
        "discount": 100
      },
      {
        "date": "2026-04-27",
        "price": 0.0,
        "discount": 100
      },
      {
        "date": "2026-04-27",
        "price": 0.0,
        "discount": 100
      },
      {
        "date": "2026-04-27",
        "price": 0.0,
        "discount": 100
      },
      {
        "date": "2026-04-27",
        "price": 0.0,
        "discount": 100
      },
      {
        "date": "2026-04-27",
        "price": 0.0,
        "discount": 100
      },
      {
        "date": "2026-04-27",
        "price": 0.0,
        "discount": 100
      },
      {
        "date": "2026-04-27",
        "price": 0.0,
        "discount": 100
      },
      {
        "date": "2026-04-27",
        "price": 0.0,
        "discount": 100
      },
      {
        "date": "2026-04-27",
        "price": 0.0,
        "discount": 100
      },
      {
        "date": "2026-04-27",
        "price": 0.0,
        "discount": 100
      },
      {
        "date": "2026-04-28",
        "price": 0.0,
        "discount": 100
      },
      {
        "date": "2026-04-28",
        "price": 0.0,
        "discount": 100
      },
      {
        "date": "2026-04-28",
        "price": 0.0,
        "discount": 100
      },
      {
        "date": "2026-04-28",
        "price": 0.0,
        "discount": 100
      },
      {
        "date": "2026-04-28",
        "price": 0.0,
        "discount": 100
      },
      {
        "date": "2026-04-28",
        "price": 0.0,
        "discount": 100
      },
      {
        "date": "2026-04-28",
        "price": 0.0,
        "discount": 100
      },
      {
        "date": "2026-04-28",
        "price": 0.0,
        "discount": 100
      },
      {
        "date": "2026-04-28",
        "price": 0.0,
        "discount": 100
      },
      {
        "date": "2026-04-28",
        "price": 0.0,
        "discount": 100
      },
      {
        "date": "2026-04-28",
        "price": 0.0,
        "discount": 100
      },
      {
        "date": "2026-04-28",
        "price": 0.0,
        "discount": 100
      },
      {
        "date": "2026-04-28",
        "price": 0.0,
        "discount": 100
      },
      {
        "date": "2026-04-28",
        "price": 0.0,
        "discount": 100
      },
      {
        "date": "2026-04-28",
        "price": 0.0,
        "discount": 100
      },
      {
        "date": "2026-04-28",
        "price": 0.0,
        "discount": 100
      },
      {
        "date": "2026-04-28",
        "price": 0.0,
        "discount": 100
      },
      {
        "date": "2026-04-28",
        "price": 0.0,
        "discount": 100
      },
      {
        "date": "2026-04-28",
        "price": 0.0,
        "discount": 100
      },
      {
        "date": "2026-04-28",
        "price": 0.0,
        "discount": 100
      },
      {
        "date": "2026-04-29",
        "price": 0.0,
        "discount": 100
      },
      {
        "date": "2026-04-29",
        "price": 0.0,
        "discount": 100
      },
      {
        "date": "2026-04-29",
        "price": 0.0,
        "discount": 100
      },
      {
        "date": "2026-04-29",
        "price": 0.0,
        "discount": 100
      },
      {
        "date": "2026-04-29",
        "price": 0.0,
        "discount": 100
      },
      {
        "date": "2026-04-29",
        "price": 0.0,
        "discount": 100
      },
      {
        "date": "2026-04-29",
        "price": 0.0,
        "discount": 100
      },
      {
        "date": "2026-04-29",
        "price": 0.0,
        "discount": 100
      },
      {
        "date": "2026-04-29",
        "price": 0.0,
        "discount": 100
      },
      {
        "date": "2026-04-29",
        "price": 0.0,
        "discount": 100
      },
      {
        "date": "2026-04-29",
        "price": 0.0,
        "discount": 100
      },
      {
        "date": "2026-04-29",
        "price": 0.0,
        "discount": 100
      },
      {
        "date": "2026-04-29",
        "price": 0.0,
        "discount": 100
      },
      {
        "date": "2026-04-29",
        "price": 0.0,
        "discount": 100
      },
      {
        "date": "2026-04-29",
        "price": 0.0,
        "discount": 100
      },
      {
        "date": "2026-04-29",
        "price": 0.0,
        "discount": 100
      },
      {
        "date": "2026-04-29",
        "price": 0.0,
        "discount": 100
      },
      {
        "date": "2026-04-29",
        "price": 0.0,
        "discount": 100
      },
      {
        "date": "2026-04-29",
        "price": 0.0,
        "discount": 100
      },
      {
        "date": "2026-04-30",
        "price": 0.0,
        "discount": 100
      },
      {
        "date": "2026-04-30",
        "price": 0.0,
        "discount": 100
      },
      {
        "date": "2026-04-30",
        "price": 0.0,
        "discount": 100
      },
      {
        "date": "2026-04-30",
        "price": 0.0,
        "discount": 100
      },
      {
        "date": "2026-04-30",
        "price": 0.0,
        "discount": 100
      },
      {
        "date": "2026-04-30",
        "price": 0.0,
        "discount": 100
      },
      {
        "date": "2026-04-30",
        "price": 0.0,
        "discount": 100
      },
      {
        "date": "2026-04-30",
        "price": 0.0,
        "discount": 100
      },
      {
        "date": "2026-04-30",
        "price": 0.0,
        "discount": 100
      },
      {
        "date": "2026-04-30",
        "price": 0.0,
        "discount": 100
      },
      {
        "date": "2026-04-30",
        "price": 0.0,
        "discount": 100
      },
      {
        "date": "2026-04-30",
        "price": 0.0,
        "discount": 100
      },
      {
        "date": "2026-04-30",
        "price": 0.0,
        "discount": 100
      },
      {
        "date": "2026-04-30",
        "price": 0.0,
        "discount": 100
      },
      {
        "date": "2026-04-30",
        "price": 0.0,
        "discount": 100
      },
      {
        "date": "2026-04-30",
        "price": 0.0,
        "discount": 100
      },
      {
        "date": "2026-04-30",
        "price": 0.0,
        "discount": 100
      },
      {
        "date": "2026-04-30",
        "price": 0.0,
        "discount": 100
      },
      {
        "date": "2026-04-30",
        "price": 0.0,
        "discount": 100
      },
      {
        "date": "2026-04-30",
        "price": 0.0,
        "discount": 100
      },
      {
        "date": "2026-04-30",
        "price": 0.0,
        "discount": 100
      },
      {
        "date": "2026-05-01",
        "price": 0.0,
        "discount": 100
      },
      {
        "date": "2026-05-01",
        "price": 0.0,
        "discount": 100
      },
      {
        "date": "2026-05-01",
        "price": 0.0,
        "discount": 100
      },
      {
        "date": "2026-05-01",
        "price": 0.0,
        "discount": 100
      },
      {
        "date": "2026-05-01",
        "price": 0.0,
        "discount": 100
      },
      {
        "date": "2026-05-01",
        "price": 0.0,
        "discount": 100
      },
      {
        "date": "2026-05-01",
        "price": 0.0,
        "discount": 100
      },
      {
        "date": "2026-05-01",
        "price": 0.0,
        "discount": 100
      },
      {
        "date": "2026-05-01",
        "price": 0.0,
        "discount": 100
      },
      {
        "date": "2026-05-01",
        "price": 0.0,
        "discount": 100
      },
      {
        "date": "2026-05-01",
        "price": 0.0,
        "discount": 100
      },
      {
        "date": "2026-05-01",
        "price": 0.0,
        "discount": 100
      }
    ]
  },
  {
    "id": "itad-018d9663-6df7-70d3-a",
    "title": "World of Warships — Marblehead Lima Pack",
    "slug": "world-of-warships-marblehead-lima-pack",
    "type": "dlc",
    "thumb": "https://assets.isthereanydeal.com/018d9663-6df7-70d3-acc5-4c091b226904/banner400.jpg?t=1774967410",
    "store": {
      "name": "Steam",
      "url": "https://itad.link/019ddf63-5e9c-7145-a257-9c28dae6d7a1/"
    },
    "price": {
      "current": 0,
      "regular": 25000,
      "currency": "KRW",
      "cut": 100
    },
    "history": {
      "lowest": 3400,
      "lowest_date": null,
      "is_lowest": true,
      "is_store_low": false
    },
    "meta": {
      "steam_appid": 934690,
      "rating": null,
      "reviews": null,
      "players_current": null,
      "owners_estimated": null,
      "tags": [],
      "platforms": [
        "windows"
      ],
      "drm": null
    },
    "popularity_score": 0.65,
    "source": "itad",
    "itad_slug": "world-of-warships-marblehead-lima-pack",
    "flag": "N",
    "updated_at": "2026-05-01T11:39:21.462030+00:00",
    "steam_meta": {
      "review_score": "Mostly Positive",
      "review_pct": 74,
      "review_count": 141,
      "languages": [
        "영어",
        "프랑스어",
        "독일어",
        "체코어",
        "일본어",
        "폴란드어",
        "러시아어",
        "태국어",
        "튀르키예어",
        "스페인어 - 스페인",
        "한국어",
        "포르투갈어 - 브라질",
        "중국어 번체",
        "이탈리아어",
        "중국어 간체",
        "우크라이나어",
        "네덜란드어"
      ],
      "has_korean": 1
    },
    "price_history": [
      {
        "date": "2026-04-30",
        "price": 0.0,
        "discount": 100
      },
      {
        "date": "2026-04-30",
        "price": 0.0,
        "discount": 100
      },
      {
        "date": "2026-04-30",
        "price": 0.0,
        "discount": 100
      },
      {
        "date": "2026-04-30",
        "price": 0.0,
        "discount": 100
      },
      {
        "date": "2026-04-30",
        "price": 0.0,
        "discount": 100
      },
      {
        "date": "2026-04-30",
        "price": 0.0,
        "discount": 100
      },
      {
        "date": "2026-05-01",
        "price": 0.0,
        "discount": 100
      },
      {
        "date": "2026-05-01",
        "price": 0.0,
        "discount": 100
      },
      {
        "date": "2026-05-01",
        "price": 0.0,
        "discount": 100
      },
      {
        "date": "2026-05-01",
        "price": 0.0,
        "discount": 100
      },
      {
        "date": "2026-05-01",
        "price": 0.0,
        "discount": 100
      },
      {
        "date": "2026-05-01",
        "price": 0.0,
        "discount": 100
      },
      {
        "date": "2026-05-01",
        "price": 0.0,
        "discount": 100
      },
      {
        "date": "2026-05-01",
        "price": 0.0,
        "discount": 100
      },
      {
        "date": "2026-05-01",
        "price": 0.0,
        "discount": 100
      },
      {
        "date": "2026-05-01",
        "price": 0.0,
        "discount": 100
      },
      {
        "date": "2026-05-01",
        "price": 0.0,
        "discount": 100
      },
      {
        "date": "2026-05-01",
        "price": 0.0,
        "discount": 100
      }
    ]
  }
]