{
  "step": "live-check",
  "status": "done",
  "timestamp": "2026-02-19T18:11:25.867976+09:00",
  "details": {
    "maxWaitSeconds": 120,
    "result": [
      {
        "url": "https://eastsea.monster/tools/subscription-add-on-attach-rate-revenue-calculator/",
        "status": 200
      },
      {
        "url": "https://eastsea.monster/tools/paywall-intro-offer-roi-calculator/",
        "status": 200
      },
      {
        "url": "https://eastsea.monster/tools/coupon-leakage-profit-impact-calculator/",
        "status": 200
      }
    ],
    "convergedAttempt": 2
  }
}